elecphys/__init__.py
elecphys/cfc.py
elecphys/conversion.py
elecphys/data_io.py
elecphys/dimensionality_reduction.py
elecphys/fourier_analysis.py
elecphys/handlers.py
elecphys/main.py
elecphys/preprocessing.py
elecphys/utils.py
elecphys/visualization.py
elecphys/matlab_scripts/convertRHD2Mat.m
ElecPhys-0.0.57.dist-info/LICENSE
ElecPhys-0.0.57.dist-info/METADATA
ElecPhys-0.0.57.dist-info/WHEEL
ElecPhys-0.0.57.dist-info/entry_points.txt
ElecPhys-0.0.57.dist-info/top_level.txt
ElecPhys-0.0.57.dist-info/RECORD
