Metadata-Version: 2.1
Name: ElecPhys
Version: 0.0.57
Summary: Electrophysiology data processing
Home-page: https://github.com/AminAlam/ElecPhys
Author: Amin Alam
License: MIT
Keywords: EEG,signal-processing,electrophysiology,data-analysis,data-visualization,data-conversion,data-preprocessing,data-loading,rhd,notch-filter,dft,stft,fourier-transform
Requires-Python: >=3.8
License-File: LICENSE
Requires-Dist: click
Requires-Dist: mat73
Requires-Dist: matplotlib
Requires-Dist: scipy
Requires-Dist: tqdm
Requires-Dist: pandas
